<?xml version="1.0" encoding="UTF-8"?>
<!DOCTYPE suite SYSTEM "http://testng.org/testng-1.0.dtd">
<suite name="All Test Suite">
    <test verbose="2" preserve-order="true"
          name="C:/Users/aijaz/IdeaProjects/APIAUTOMATION_PROGRAM/src/test/java/org/Ijaj/ex05_PUT_Request">
        <classes>
            <class name="org.Ijaj.ex05_PUT_Request.APITesting_PUT_NonBDDStyle">
                <methods>
                    <include name="test_put_NonBDD"/>
                </methods>
            </class>
        </classes>
    </test>
</suite>